python_wheel_to_conda_package/__init__.py
python_wheel_to_conda_package/__main__.py
python_wheel_to_conda_package/_get_conda_info_files.py
python_wheel_to_conda_package/_get_conda_package_match_specification.py
python_wheel_to_conda_package/_get_dist_info_folder_name.py
python_wheel_to_conda_package/_get_wheel_folder_path.py
python_wheel_to_conda_package/_get_wheel_path_to_conda_path.py
python_wheel_to_conda_package/_read_zip_file.py
python_wheel_to_conda_package/_wheel_dist_info.py
python_wheel_to_conda_package/py.typed
python_wheel_to_conda_package/python_wheel_to_conda_package.py
python_wheel_to_conda_package-0.4.1.dist-info/METADATA
python_wheel_to_conda_package-0.4.1.dist-info/WHEEL
python_wheel_to_conda_package-0.4.1.dist-info/entry_points.txt
python_wheel_to_conda_package-0.4.1.dist-info/licenses/LICENSE
python_wheel_to_conda_package-0.4.1.dist-info/RECORD
