Metadata-Version: 2.3
Name: python-wheel-to-conda-package
Version: 0.4.1
Summary: Convert a Pure-Python Wheel to a noarch Conda package
Project-URL: Repository, https://github.com/tibdex/python-wheel-to-conda-package
Author-email: Thibault Derousseaux <tibdex@gmail.com>
License-File: LICENSE
Keywords: conda,conda-package,python-wheel,wheel
Classifier: Development Status :: 4 - Beta
Classifier: License :: OSI Approved :: MIT License
Classifier: Operating System :: OS Independent
Classifier: Topic :: Software Development :: Build Tools
Classifier: Typing :: Typed
Requires-Python: >=3.10
Requires-Dist: packaging>=23.0
